{
  "name": "Naafiri",
  "adaptative_type": "Physical",
  "attack_type": "Melee",
  "positions": [
    "Middle"
  ],
  "stats": {
    "health": {
      "flat": 610.0,
      "perLevel": 105.0
    },
    "mana": {
      "flat": 400.0,
      "perLevel": 55.0
    },
    "armor": {
      "flat": 28.0,
      "perLevel": 4.2
    },
    "magicResistance": {
      "flat": 32.0,
      "perLevel": 2.05
    },
    "attackDamage": {
      "flat": 55.0,
      "perLevel": 2.0
    },
    "attackSpeed": {
      "flat": 0.663,
      "perLevel": 2.1
    },
    "movespeed": {
      "flat": 340.0,
      "perLevel": 0.0
    },
    "criticalStrikeDamage": {
      "flat": 175.0,
      "perLevel": 0.0
    },
    "criticalStrikeDamageModifier": {
      "flat": 1.0,
      "perLevel": 0.0
    },
    "attackSpeedRatio": {
      "flat": 0.625,
      "perLevel": 0.0
    },
    "attackRange": {
      "flat": 125.0,
      "perLevel": 0.0
    },
    "aramDamageTaken": {
      "flat": 1.0,
      "perLevel": 0.0
    },
    "aramDamageDealt": {
      "flat": 1.1,
      "perLevel": 0.0
    },
    "urfDamageTaken": {
      "flat": 1.0,
      "perLevel": 0.0
    },
    "urfDamageDealt": {
      "flat": 1.0,
      "perLevel": 0.0
    }
  },
  "abilities": [
    [
      {
        "type": "E",
        "name": "_1"
      },
      {
        "name": "Eviscerate",
        "damage_type": "Physical",
        "attributes": "Undefined",
        "damage": [
          "15 + (0.4 * ctx.bonus_ad)",
          "25 + (0.4 * ctx.bonus_ad)",
          "35 + (0.4 * ctx.bonus_ad)",
          "45 + (0.4 * ctx.bonus_ad)",
          "55 + (0.4 * ctx.bonus_ad)"
        ]
      }
    ],
    [
      {
        "type": "E",
        "name": "_2"
      },
      {
        "name": "Eviscerate",
        "damage_type": "Physical",
        "attributes": "Undefined",
        "damage": [
          "60 + (0.8 * ctx.bonus_ad)",
          "85 + (0.8 * ctx.bonus_ad)",
          "110 + (0.8 * ctx.bonus_ad)",
          "135 + (0.8 * ctx.bonus_ad)",
          "160 + (0.8 * ctx.bonus_ad)"
        ]
      }
    ],
    [
      {
        "type": "Q",
        "name": "_2"
      },
      {
        "name": "Darkin Daggers",
        "damage_type": "Physical",
        "attributes": "Undefined",
        "damage": [
          "35 + (0.2 * ctx.bonus_ad)",
          "40 + (0.2 * ctx.bonus_ad)",
          "45 + (0.2 * ctx.bonus_ad)",
          "50 + (0.2 * ctx.bonus_ad)",
          "55 + (0.2 * ctx.bonus_ad)"
        ]
      }
    ],
    [
      {
        "type": "E",
        "name": "_3"
      },
      {
        "name": "Eviscerate",
        "damage_type": "Physical",
        "attributes": "Undefined",
        "damage": [
          "75 + (1.2 * ctx.bonus_ad)",
          "110 + (1.2 * ctx.bonus_ad)",
          "145 + (1.2 * ctx.bonus_ad)",
          "180 + (1.2 * ctx.bonus_ad)",
          "215 + (1.2 * ctx.bonus_ad)"
        ]
      }
    ],
    [
      {
        "type": "Q",
        "name": "_1"
      },
      {
        "name": "Darkin Daggers",
        "damage_type": "Physical",
        "attributes": "Undefined",
        "damage": [
          "3.5 + (0.08 * ctx.bonus_ad)",
          "6 + (0.08 * ctx.bonus_ad)",
          "8.5 + (0.08 * ctx.bonus_ad)",
          "11 + (0.08 * ctx.bonus_ad)",
          "13.5 + (0.08 * ctx.bonus_ad)"
        ]
      }
    ],
    [
      {
        "type": "R",
        "name": "_1"
      },
      {
        "name": "Hounds' Pursuit",
        "damage_type": "Physical",
        "attributes": "Undefined",
        "damage": [
          "150 + (1.2 * ctx.bonus_ad)",
          "250 + (1.2 * ctx.bonus_ad)",
          "350 + (1.2 * ctx.bonus_ad)"
        ]
      }
    ],
    [
      {
        "type": "Q",
        "name": "_3"
      },
      {
        "name": "Darkin Daggers",
        "damage_type": "Physical",
        "attributes": "Undefined",
        "damage": [
          "35 + (0.8 * ctx.bonus_ad)",
          "60 + (0.8 * ctx.bonus_ad)",
          "85 + (0.8 * ctx.bonus_ad)",
          "110 + (0.8 * ctx.bonus_ad)",
          "135 + (0.8 * ctx.bonus_ad)"
        ]
      }
    ],
    [
      {
        "type": "Q",
        "name": "_6"
      },
      {
        "name": "Darkin Daggers",
        "damage_type": "Physical",
        "attributes": "Undefined",
        "damage": [
          "130 + (2.4 * ctx.bonus_ad)",
          "190 + (2.4 * ctx.bonus_ad)",
          "250 + (2.4 * ctx.bonus_ad)",
          "310 + (2.4 * ctx.bonus_ad)",
          "370 + (2.4 * ctx.bonus_ad)"
        ]
      }
    ],
    [
      {
        "type": "Q",
        "name": "_8"
      },
      {
        "name": "Darkin Daggers",
        "damage_type": "Physical",
        "attributes": "Undefined",
        "damage": [
          "100 + (1.4 * ctx.bonus_ad)",
          "145 + (1.4 * ctx.bonus_ad)",
          "190 + (1.4 * ctx.bonus_ad)",
          "235 + (1.4 * ctx.bonus_ad)",
          "280 + (1.4 * ctx.bonus_ad)"
        ]
      }
    ],
    [
      {
        "type": "Q",
        "name": "_7"
      },
      {
        "name": "Darkin Daggers",
        "damage_type": "Physical",
        "attributes": "Undefined",
        "damage": [
          "30 + (0.4 * ctx.bonus_ad)",
          "45 + (0.4 * ctx.bonus_ad)",
          "60 + (0.4 * ctx.bonus_ad)",
          "75 + (0.4 * ctx.bonus_ad)",
          "90 + (0.4 * ctx.bonus_ad)"
        ]
      }
    ],
    [
      {
        "type": "Q",
        "name": "_5"
      },
      {
        "name": "Darkin Daggers",
        "damage_type": "Physical",
        "attributes": "Undefined",
        "damage": [
          "60 + (1.4 * ctx.bonus_ad)",
          "90 + (1.4 * ctx.bonus_ad)",
          "120 + (1.4 * ctx.bonus_ad)",
          "150 + (1.4 * ctx.bonus_ad)",
          "180 + (1.4 * ctx.bonus_ad)"
        ]
      }
    ],
    [
      {
        "type": "Q",
        "name": "_4"
      },
      {
        "name": "Darkin Daggers",
        "damage_type": "Physical",
        "attributes": "Undefined",
        "damage": [
          "70 + ctx.bonus_ad",
          "100 + ctx.bonus_ad",
          "130 + ctx.bonus_ad",
          "160 + ctx.bonus_ad",
          "190 + ctx.bonus_ad"
        ]
      }
    ],
    [
      {
        "type": "R",
        "name": "_2"
      },
      {
        "name": "Hounds' Pursuit",
        "damage_type": "Physical",
        "attributes": "Undefined",
        "damage": [
          "15 + (0.12 * ctx.bonus_ad)",
          "25 + (0.12 * ctx.bonus_ad)",
          "35 + (0.12 * ctx.bonus_ad)"
        ]
      }
    ]
  ],
  "merge_data": []
}