{
  "colloq": "",
  "description": "<mainText><stats><attention>300</attention> Health<br><attention>25</attention> Armor<br><attention>15</attention> Ability Haste<br><attention>30</attention> Magic Resist</stats><br><br><passive>Frostfire Tempest</passive><br>Casting your Ultimate summons a storm around you for 5 seconds. The storm deals <magicDamage> magic damage</magicDamage> per second to enemy champions and <keyword>Slows</keyword> them by 30%.</mainText>",
  "gold": {
    "base": 2500,
    "purchasable": true,
    "sell": 1250,
    "total": 2500
  },
  "image": {
    "full": "223050.png",
    "group": "item",
    "h": 48,
    "sprite": "item1.png",
    "w": 48,
    "x": 0,
    "y": 384
  },
  "maps": {
    "11": false,
    "12": false,
    "21": false,
    "22": false,
    "30": true,
    "33": false,
    "35": false
  },
  "name": "Zeke's Convergence",
  "plaintext": "",
  "stats": {
    "FlatArmorMod": 25,
    "FlatHPPoolMod": 300,
    "FlatSpellBlockMod": 30
  },
  "tags": [
    "Health",
    "SpellBlock",
    "Armor",
    "AbilityHaste"
  ]
}