{
  "colloq": ";",
  "depth": 3,
  "description": "<mainText><stats><attention>65</attention> Attack Damage<br><attention>15</attention> Ability Haste<br><attention>12%</attention> Life Steal</stats><br><br><passive>Cleave</passive><br>Attacks deal <physicalDamage>physical damage</physicalDamage> to nearby enemies.<active>Ravenous Crescent</active><br>Deal <physicalDamage>physical damage</physicalDamage> to enemies around you. <br>Your Life Steal applies to this damage.</mainText>",
  "from": [
    "3077",
    "1053",
    "3133"
  ],
  "gold": {
    "base": 150,
    "purchasable": true,
    "sell": 2310,
    "total": 3300
  },
  "image": {
    "full": "3074.png",
    "group": "item",
    "h": 48,
    "sprite": "item3.png",
    "w": 48,
    "x": 144,
    "y": 240
  },
  "maps": {
    "11": true,
    "12": true,
    "21": true,
    "22": false,
    "30": false,
    "33": false,
    "35": true
  },
  "name": "Ravenous Hydra",
  "plaintext": "Melee attacks hit nearby enemies, dealing damage and restoring Health",
  "stats": {
    "FlatPhysicalDamageMod": 65,
    "PercentLifeStealMod": 0.12
  },
  "tags": [
    "Damage",
    "LifeSteal",
    "CooldownReduction",
    "OnHit",
    "AbilityHaste"
  ]
}