{
  "allytips": [
    "Storing a stun for use with her ultimate can turn the tide of a team fight.",
    "Striking killing blows on minions with Disintegrate enables Annie to farm extremely well early in the game.",
    "Molten Shield is a good spell to cast to work up to Annie's stun, so sometimes it's beneficial to grab at least 1 rank in it early."
  ],
  "blurb": "Dangerous, yet disarmingly precocious, Annie is a child mage with immense pyromantic power. Even in the shadows of the mountains north of Noxus, she is a magical outlier. Her natural affinity for fire manifested early in life through unpredictable...",
  "enemytips": [
    "Annie's summoned bear, Tibbers, burns opposing units around himself. Try to keep your distance from him after he's been summoned.",
    "Summoner Smite can be used to help take down Tibbers.",
    "Keep an eye out for a white, swirling power around Annie. It means she's ready to unleash her stun."
  ],
  "id": "Annie",
  "image": {
    "full": "Annie.png",
    "group": "champion",
    "h": 48,
    "sprite": "champion0.png",
    "w": 48,
    "x": 384,
    "y": 0
  },
  "info": {
    "attack": 2,
    "defense": 3,
    "difficulty": 6,
    "magic": 10
  },
  "key": "1",
  "lore": "Dangerous, yet disarmingly precocious, Annie is a child mage with immense pyromantic power. Even in the shadows of the mountains north of Noxus, she is a magical outlier. Her natural affinity for fire manifested early in life through unpredictable, emotional outbursts, though she eventually learned to control these “playful tricks.” Her favorite includes the summoning of her beloved teddy bear, Tibbers, as a fiery protector. Lost in the perpetual innocence of childhood, Annie wanders the dark forests, always looking for someone to play with.",
  "name": "Annie",
  "partype": "Mana",
  "passive": {
    "description": "After casting 4 spells, Annie's next offensive spell will stun the target.<br><br>Annie begins the game and respawns with Pyromania available.",
    "image": {
      "full": "Annie_Passive.png",
      "group": "passive",
      "h": 48,
      "sprite": "passive0.png",
      "w": 48,
      "x": 384,
      "y": 0
    },
    "name": "Pyromania"
  },
  "recommended": [],
  "skins": [
    {
      "chromas": false,
      "id": "1000",
      "name": "default",
      "num": 0
    },
    {
      "chromas": false,
      "id": "1001",
      "name": "Goth Annie",
      "num": 1
    },
    {
      "chromas": false,
      "id": "1002",
      "name": "Red Riding Annie",
      "num": 2
    },
    {
      "chromas": false,
      "id": "1003",
      "name": "Annie in Wonderland",
      "num": 3
    },
    {
      "chromas": false,
      "id": "1004",
      "name": "Prom Queen Annie",
      "num": 4
    },
    {
      "chromas": false,
      "id": "1005",
      "name": "Frostfire Annie",
      "num": 5
    },
    {
      "chromas": false,
      "id": "1006",
      "name": "Reverse Annie",
      "num": 6
    },
    {
      "chromas": false,
      "id": "1007",
      "name": "FrankenTibbers Annie",
      "num": 7
    },
    {
      "chromas": false,
      "id": "1008",
      "name": "Panda Annie",
      "num": 8
    },
    {
      "chromas": false,
      "id": "1009",
      "name": "Sweetheart Annie",
      "num": 9
    },
    {
      "chromas": false,
      "id": "1010",
      "name": "Hextech Annie",
      "num": 10
    },
    {
      "chromas": false,
      "id": "1011",
      "name": "Super Galaxy Annie",
      "num": 11
    },
    {
      "chromas": false,
      "id": "1012",
      "name": "Annie-Versary",
      "num": 12
    },
    {
      "chromas": true,
      "id": "1013",
      "name": "Lunar Beast Annie",
      "num": 13
    },
    {
      "chromas": false,
      "id": "1022",
      "name": "Cafe Cuties Annie",
      "num": 22
    },
    {
      "chromas": false,
      "id": "1031",
      "name": "Fright Night Annie",
      "num": 31
    },
    {
      "chromas": false,
      "id": "1040",
      "name": "Winterblessed Annie",
      "num": 40
    },
    {
      "chromas": false,
      "id": "1050",
      "name": "Battle Princess Annie",
      "num": 50
    }
  ],
  "spells": [
    {
      "cooldown": [
        4,
        4,
        4,
        4,
        4
      ],
      "cooldownBurn": "4",
      "cost": [
        60,
        65,
        70,
        75,
        80
      ],
      "costBurn": "60/65/70/75/80",
      "costType": " {{ abilityresourcename }}",
      "datavalues": {},
      "description": "Annie hurls a Mana infused fireball, dealing damage and refunding the Mana cost if it destroys the target.",
      "effect": [
        null,
        [
          0,
          0,
          0,
          0,
          0
        ],
        [
          0,
          0,
          0,
          0,
          0
        ],
        [
          0,
          0,
          0,
          0,
          0
        ],
        [
          0,
          0,
          0,
          0,
          0
        ],
        [
          0,
          0,
          0,
          0,
          0
        ],
        [
          0,
          0,
          0,
          0,
          0
        ],
        [
          0,
          0,
          0,
          0,
          0
        ],
        [
          0,
          0,
          0,
          0,
          0
        ],
        [
          0,
          0,
          0,
          0,
          0
        ],
        [
          0,
          0,
          0,
          0,
          0
        ]
      ],
      "effectBurn": [
        null,
        "0",
        "0",
        "0",
        "0",
        "0",
        "0",
        "0",
        "0",
        "0",
        "0"
      ],
      "id": "AnnieQ",
      "image": {
        "full": "AnnieQ.png",
        "group": "spell",
        "h": 48,
        "sprite": "spell1.png",
        "w": 48,
        "x": 0,
        "y": 48
      },
      "leveltip": {
        "effect": [
          "{{ basedamage }} -> {{ basedamageNL }}",
          "{{ cost }} -> {{ costNL }}"
        ],
        "label": [
          "Damage",
          "@AbilityResourceName@ Cost"
        ]
      },
      "maxammo": "-1",
      "maxrank": 5,
      "name": "Disintegrate",
      "range": [
        625,
        625,
        625,
        625,
        625
      ],
      "rangeBurn": "625",
      "resource": "{{ cost }} {{ abilityresourcename }}",
      "tooltip": "Annie hurls a fireball, dealing <magicDamage>{{ totaldamage }} magic damage</magicDamage>. If the target dies, Annie refunds the Mana cost and reduces the Cooldown by 50%.{{ spellmodifierdescriptionappend }}",
      "vars": []
    },
    {
      "cooldown": [
        7,
        7,
        7,
        7,
        7
      ],
      "cooldownBurn": "7",
      "cost": [
        70,
        75,
        80,
        85,
        90
      ],
      "costBurn": "70/75/80/85/90",
      "costType": " {{ abilityresourcename }}",
      "datavalues": {},
      "description": "Annie casts a blazing cone of fire, dealing damage to all enemies in the area.",
      "effect": [
        null,
        [
          0,
          0,
          0,
          0,
          0
        ],
        [
          0,
          0,
          0,
          0,
          0
        ],
        [
          0,
          0,
          0,
          0,
          0
        ],
        [
          0,
          0,
          0,
          0,
          0
        ],
        [
          0,
          0,
          0,
          0,
          0
        ],
        [
          0,
          0,
          0,
          0,
          0
        ],
        [
          0,
          0,
          0,
          0,
          0
        ],
        [
          0,
          0,
          0,
          0,
          0
        ],
        [
          0,
          0,
          0,
          0,
          0
        ],
        [
          0,
          0,
          0,
          0,
          0
        ]
      ],
      "effectBurn": [
        null,
        "0",
        "0",
        "0",
        "0",
        "0",
        "0",
        "0",
        "0",
        "0",
        "0"
      ],
      "id": "AnnieW",
      "image": {
        "full": "AnnieW.png",
        "group": "spell",
        "h": 48,
        "sprite": "spell1.png",
        "w": 48,
        "x": 48,
        "y": 48
      },
      "leveltip": {
        "effect": [
          "{{ basedamage }} -> {{ basedamageNL }}",
          "{{ cost }} -> {{ costNL }}"
        ],
        "label": [
          "Damage",
          "@AbilityResourceName@ Cost"
        ]
      },
      "maxammo": "-1",
      "maxrank": 5,
      "name": "Incinerate",
      "range": [
        600,
        600,
        600,
        600,
        600
      ],
      "rangeBurn": "600",
      "resource": "{{ cost }} {{ abilityresourcename }}",
      "tooltip": "Annie projects a wave of fire, dealing <magicDamage>{{ totaldamage }} magic damage</magicDamage>.{{ spellmodifierdescriptionappend }}",
      "vars": []
    },
    {
      "cooldown": [
        12,
        11.5,
        11,
        10.5,
        10
      ],
      "cooldownBurn": "12/11.5/11/10.5/10",
      "cost": [
        60,
        65,
        70,
        75,
        80
      ],
      "costBurn": "60/65/70/75/80",
      "costType": " {{ abilityresourcename }}",
      "datavalues": {},
      "description": "Grants Annie or an ally a shield, a burst of Move Speed, and damages enemies who strike her with attacks or spells.",
      "effect": [
        null,
        [
          0,
          0,
          0,
          0,
          0
        ],
        [
          0,
          0,
          0,
          0,
          0
        ],
        [
          0,
          0,
          0,
          0,
          0
        ],
        [
          0,
          0,
          0,
          0,
          0
        ],
        [
          0,
          0,
          0,
          0,
          0
        ],
        [
          0,
          0,
          0,
          0,
          0
        ],
        [
          0,
          0,
          0,
          0,
          0
        ],
        [
          0,
          0,
          0,
          0,
          0
        ],
        [
          0,
          0,
          0,
          0,
          0
        ],
        [
          0,
          0,
          0,
          0,
          0
        ]
      ],
      "effectBurn": [
        null,
        "0",
        "0",
        "0",
        "0",
        "0",
        "0",
        "0",
        "0",
        "0",
        "0"
      ],
      "id": "AnnieE",
      "image": {
        "full": "AnnieE.png",
        "group": "spell",
        "h": 48,
        "sprite": "spell1.png",
        "w": 48,
        "x": 96,
        "y": 48
      },
      "leveltip": {
        "effect": [
          "{{ shieldamount }} -> {{ shieldamountNL }}",
          "{{ damagereflection }} -> {{ damagereflectionNL }}",
          "{{ cooldown }} -> {{ cooldownNL }}",
          "{{ cost }} -> {{ costNL }}"
        ],
        "label": [
          "Shield Health",
          "Damage Reflection",
          "Cooldown",
          "@AbilityResourceName@ Cost"
        ]
      },
      "maxammo": "-1",
      "maxrank": 5,
      "name": "Molten Shield",
      "range": [
        800,
        800,
        800,
        800,
        800
      ],
      "rangeBurn": "800",
      "resource": "{{ cost }} {{ abilityresourcename }}",
      "tooltip": "Annie grants an ally champion <shield>{{ shieldblocktotal }} Shield</shield> for {{ shieldduration }} seconds and <speed>{{ movespeedcalc }} Decaying Move Speed</speed> for {{ movementspeedduration }} seconds. While the shield holds, enemies who hit the shielded ally with an Attack or Ability receive <magicDamage>{{ damagereturn }} magic damage</magicDamage> once per shield.<br /><br />Tibbers always gains the effects of <spellName>Molten Shield</spellName> when summoned.{{ spellmodifierdescriptionappend }}",
      "vars": []
    },
    {
      "cooldown": [
        130,
        115,
        100
      ],
      "cooldownBurn": "130/115/100",
      "cost": [
        100,
        100,
        100
      ],
      "costBurn": "100",
      "costType": " {{ abilityresourcename }}",
      "datavalues": {},
      "description": "Annie wills her bear Tibbers to life, dealing damage to units in the area. Tibbers can attack and also burns enemies that stand near him.",
      "effect": [
        null,
        [
          0,
          0,
          0
        ],
        [
          0,
          0,
          0
        ],
        [
          0,
          0,
          0
        ],
        [
          0,
          0,
          0
        ],
        [
          0,
          0,
          0
        ],
        [
          0,
          0,
          0
        ],
        [
          0,
          0,
          0
        ],
        [
          0,
          0,
          0
        ],
        [
          0,
          0,
          0
        ],
        [
          0,
          0,
          0
        ]
      ],
      "effectBurn": [
        null,
        "0",
        "0",
        "0",
        "0",
        "0",
        "0",
        "0",
        "0",
        "0",
        "0"
      ],
      "id": "AnnieR",
      "image": {
        "full": "AnnieR.png",
        "group": "spell",
        "h": 48,
        "sprite": "spell1.png",
        "w": 48,
        "x": 144,
        "y": 48
      },
      "leveltip": {
        "effect": [
          "{{ initialdamage }} -> {{ initialdamageNL }}",
          "{{ auradamage }} -> {{ auradamageNL }}",
          "{{ tibbersattackdamage }} -> {{ tibbersattackdamageNL }}",
          "{{ tibbersbonusms }} -> {{ tibbersbonusmsNL }}",
          "{{ cooldown }} -> {{ cooldownNL }}",
          "{{ rpercentpenbuff*100.000000 }}% -> {{ rpercentpenbuffnl*100.000000 }}%"
        ],
        "label": [
          "Initial Damage",
          "Aura Damage",
          "Attack Damage",
          "Bonus Move Speed",
          "Cooldown",
          "Magic Penetration"
        ]
      },
      "maxammo": "-1",
      "maxrank": 3,
      "name": "Summon: Tibbers",
      "range": [
        600,
        600,
        600
      ],
      "rangeBurn": "600",
      "resource": "{{ cost }} {{ abilityresourcename }}",
      "tooltip": "<spellPassive>Passive:</spellPassive> Annie gains {{ rpercentpenbuff*100 }}% Magic Penetration.<br /><br />Annie summons her bear Tibbers, dealing <magicDamage>{{ initialburstdamage }} magic damage</magicDamage>. For the next {{ tibberslifetime }} seconds, Tibbers burns nearby enemies for <magicDamage>{{ tibbersauradamage }} magic damage per second</magicDamage>.<br /><br />Tibbers becomes enraged when summoned, if Annie stuns an enemy champion, and if Annie dies. When enraged, Tibbers gains <attackSpeed>275% Attack Speed</attackSpeed> and <speed>100% Move Speed</speed> decaying over 3 seconds.<br /><br /><recast>Recast:</recast> Manually issue orders to Tibbers.{{ spellmodifierdescriptionappend }}",
      "vars": []
    }
  ],
  "stats": {
    "armor": 23,
    "armorperlevel": 4,
    "attackdamage": 50,
    "attackdamageperlevel": 2.65,
    "attackrange": 625,
    "attackspeed": 0.61,
    "attackspeedperlevel": 1.36,
    "crit": 0,
    "critperlevel": 0,
    "hp": 560,
    "hpperlevel": 96,
    "hpregen": 5.5,
    "hpregenperlevel": 0.55,
    "movespeed": 335,
    "mp": 418,
    "mpperlevel": 25,
    "mpregen": 8,
    "mpregenperlevel": 0.8,
    "spellblock": 30,
    "spellblockperlevel": 1.3
  },
  "tags": [
    "Mage",
    "Support"
  ],
  "title": "the Dark Child"
}